cod/__init__.py
cod/cod.py
cod/demo.py
cod-0.0.4.dist-info/LICENSE
cod-0.0.4.dist-info/METADATA
cod-0.0.4.dist-info/WHEEL
cod-0.0.4.dist-info/top_level.txt
cod-0.0.4.dist-info/RECORD
