Metadata-Version: 2.1
Name: cod
Version: 0.0.4
Summary: A userful package to use 'the click package to add command' for a interactive terminal
Home-page: https://github.com/Yyonging/cod
Author: duanyongqiang
Author-email: sysuduanyongqiang@163.com
License: Apache License 2.0
Platform: UNKNOWN
Classifier: Programming Language :: Python :: 3
Classifier: License :: OSI Approved :: GNU General Public License v2 (GPLv2)
Classifier: Operating System :: OS Independent
Requires-Python: >=3.6
Requires-Dist: prompt-toolkit (>=3.0.0)
Requires-Dist: click (>=5.1)
